blayers/__init__.py
blayers/_utils.py
blayers/infer.py
blayers/layers.py
blayers/links.py
blayers/sampling.py
blayers-0.2.3.dist-info/licenses/LICENSE
docs/conf.py
tests/__init__.py
tests/infer_test.py
tests/layers_test.py
tests/links_test.py
tests/utils_test.py
blayers-0.2.3.dist-info/METADATA
blayers-0.2.3.dist-info/WHEEL
blayers-0.2.3.dist-info/top_level.txt
blayers-0.2.3.dist-info/RECORD
