Metadata-Version: 2.4
Name: blayers
Version: 0.2.3
Summary: Bayesian layers for NumPyro and Jax
Author-email: George Berry <george.e.berry@gmail.com>
Project-URL: Homepage, https://github.com/georgeberry/blayers
Project-URL: Documentation, https://georgeberry.github.io/blayers/
Requires-Python: >=3.9
License-File: LICENSE
Requires-Dist: jax
Requires-Dist: numpyro
Requires-Dist: optax
Provides-Extra: dev
Requires-Dist: optax; extra == "dev"
Requires-Dist: pytest; extra == "dev"
Requires-Dist: pytest-check; extra == "dev"
Requires-Dist: mypy; extra == "dev"
Requires-Dist: black; extra == "dev"
Requires-Dist: isort; extra == "dev"
Requires-Dist: autoflake; extra == "dev"
Requires-Dist: sphinx; extra == "dev"
Requires-Dist: sphinx-book-theme; extra == "dev"
Requires-Dist: furo; extra == "dev"
Requires-Dist: coverage; extra == "dev"
Requires-Dist: pytest-cov; extra == "dev"
Requires-Dist: pre-commit; extra == "dev"
Requires-Dist: myst-parser; extra == "dev"
Dynamic: license-file
